subproc/__init__.py
subproc/subproc.py
subproc-0.0.1.dev7.dist-info/LICENSE
subproc-0.0.1.dev7.dist-info/WHEEL
subproc-0.0.1.dev7.dist-info/METADATA
subproc-0.0.1.dev7.dist-info/RECORD
