Metadata-Version: 2.1
Name: subproc
Version: 0.0.1.dev7
Summary: Provides utility functions around subprocess module.
License: Apache-2.0
Author: Mustafa Caylak
Author-email: mustafa.caylak@web.de
Classifier: License :: OSI Approved :: Apache Software License
Classifier: Programming Language :: Python :: 2
Classifier: Programming Language :: Python :: 2.7
Classifier: Programming Language :: Python :: 3
Classifier: Programming Language :: Python :: 3.4
Classifier: Programming Language :: Python :: 3.5
Classifier: Programming Language :: Python :: 3.6
Classifier: Programming Language :: Python :: 3.7
